manuscriptmonitor/__about__.py
manuscriptmonitor/__init__.py
manuscriptmonitor/__main__.py
manuscriptmonitor/manuscriptmonitor.py
manuscriptmonitor-0.6.0.dist-info/METADATA
manuscriptmonitor-0.6.0.dist-info/WHEEL
manuscriptmonitor-0.6.0.dist-info/licenses/LICENSE.txt
manuscriptmonitor-0.6.0.dist-info/RECORD
